deps/__init__.py
deps/oai/__init__.py
deps/oai/batch_api/__init__.py
deps/oai/batch_api/batch_api.py
openai_batch_sdk/__init__.py
openai_batch_sdk/core.py
openai_batch_sdk/event_handler.py
utils/__init__.py
utils/env.py
utils/logging.py
utils/project.py
openai_batch_sdk-0.1.3.dist-info/METADATA
openai_batch_sdk-0.1.3.dist-info/WHEEL
openai_batch_sdk-0.1.3.dist-info/entry_points.txt
openai_batch_sdk-0.1.3.dist-info/top_level.txt
openai_batch_sdk-0.1.3.dist-info/RECORD
