Metadata-Version: 2.1
Name: openai_batch_sdk
Version: 0.1.3
Summary: An SDK for OpenAI ChatGPT batch API for a single process.
Home-page: https://github.com/adico1/openai_batch_sdk
Author: adico
Author-email: adico1@gamil.com
Classifier: Programming Language :: Python :: 3
Classifier: License :: OSI Approved :: MIT License
Classifier: Operating System :: OS Independent
Requires-Python: >=3.6
Requires-Dist: openai
Requires-Dist: python-dotenv
